pmpcontrol/__init__.py
pmpcontrol/controller.py
pmpcontrol-0.0.3.dist-info/METADATA
pmpcontrol-0.0.3.dist-info/WHEEL
pmpcontrol-0.0.3.dist-info/licenses/LICENSE
pmpcontrol-0.0.3.dist-info/RECORD
