Metadata-Version: 2.3
Name: pmpcontrol
Version: 0.0.3
Summary: A Python interface for interacting with the iCON Platform M+ MIDI control surface. 
Project-URL: Homepage, https://github.com/Kay0n/pmpcontrol
Project-URL: Issues, https://github.com/Kay0n/pmpcontrol/issues
Author-email: Kay0n <kayon5555@gmail.com>
License-File: LICENSE
Classifier: License :: OSI Approved :: MIT License
Classifier: Operating System :: OS Independent
Classifier: Programming Language :: Python :: 3
Requires-Python: >=3.9
Requires-Dist: python-rtmidi
